igmp/Interface.py
igmp/InterfaceIGMP.py
igmp/__init__.py
igmp/utils.py
igmp/igmp2/GroupState.py
igmp/igmp2/RouterState.py
igmp/igmp2/__init__.py
igmp/igmp2/igmp_globals.py
igmp/igmp2/nonquerier/CheckingMembership.py
igmp/igmp2/nonquerier/MembersPresent.py
igmp/igmp2/nonquerier/NoMembersPresent.py
igmp/igmp2/nonquerier/NonQuerier.py
igmp/igmp2/nonquerier/__init__.py
igmp/igmp2/querier/CheckingMembership.py
igmp/igmp2/querier/MembersPresent.py
igmp/igmp2/querier/NoMembersPresent.py
igmp/igmp2/querier/Querier.py
igmp/igmp2/querier/Version1MembersPresent.py
igmp/igmp2/querier/__init__.py
igmp/igmp2/wrapper/CheckingMembership.py
igmp/igmp2/wrapper/MembersPresent.py
igmp/igmp2/wrapper/NoMembersPresent.py
igmp/igmp2/wrapper/Version1MembersPresent.py
igmp/igmp2/wrapper/__init__.py
igmp/packet/Packet.py
igmp/packet/PacketIGMPHeader.py
igmp/packet/PacketIpHeader.py
igmp/packet/PacketPayload.py
igmp/packet/ReceivedPacket.py
igmp/packet/__init__.py
igmp/rwlock/RWLock.py
igmp/rwlock/__init__.py
igmp-1.0.4.dist-info/LICENSE
igmp-1.0.4.dist-info/METADATA
igmp-1.0.4.dist-info/WHEEL
igmp-1.0.4.dist-info/top_level.txt
igmp-1.0.4.dist-info/RECORD
