Metadata-Version: 2.1
Name: igmp
Version: 1.0.4
Summary: IGMPv2 router-side protocol implementation for Python
Home-page: http://github.com/pedrofran12/igmp
Author: Pedro Oliveira
Author-email: pedro.francisco.oliveira@tecnico.ulisboa.pt
License: MIT
Keywords: IGMP IGMPv2 Router IPv4 Multicast Interest
Platform: any
Classifier: Development Status :: 4 - Beta
Classifier: Environment :: Console
Classifier: Intended Audience :: Information Technology
Classifier: Topic :: System :: Networking
Classifier: License :: OSI Approved :: MIT License
Classifier: Natural Language :: English
Classifier: Operating System :: OS Independent
Classifier: Programming Language :: Python
Classifier: Programming Language :: Python :: 3
Classifier: Programming Language :: Python :: 3.2
Classifier: Programming Language :: Python :: 3.3
Classifier: Programming Language :: Python :: 3.4
Classifier: Programming Language :: Python :: 3.5
Classifier: Programming Language :: Python :: 3.6
Classifier: Programming Language :: Python :: 3.7
Classifier: Programming Language :: Python :: 3.8
Classifier: Programming Language :: Python :: 3.9
Requires-Python: >=3.2
License-File: LICENSE
Requires-Dist: netifaces
Requires-Dist: ipaddress
